m3_gar_constants/__init__.py
m3_gar_constants/version.py
m3_gar_constants-1.0.4.dist-info/METADATA
m3_gar_constants-1.0.4.dist-info/WHEEL
m3_gar_constants-1.0.4.dist-info/top_level.txt
m3_gar_constants-1.0.4.dist-info/RECORD
